OverTheShellbags/__init__.py
OverTheShellbags/converter.py
OverTheShellbags/extension_block_parser.py
OverTheShellbags/parser.py
OverTheShellbags/shell_item_parser.py
OverTheShellbags/storage_property_parser.py
OverTheShellbags/defined_list/__init__.py
OverTheShellbags/defined_list/data_format.py
OverTheShellbags/defined_list/data_id.py
OverTheShellbags/defined_list/data_type.py
OverTheShellbags/defined_list/guids.py
OverTheShellbags-0.1.0.dist-info/METADATA
OverTheShellbags-0.1.0.dist-info/WHEEL
OverTheShellbags-0.1.0.dist-info/top_level.txt
OverTheShellbags-0.1.0.dist-info/RECORD
