Metadata-Version: 2.1
Name: OverTheShellbags
Version: 0.1.0
Summary: Windows Shell Item parser for shellbags' data.
Home-page: https://github.com/49374/OverTheShellbags
Author: 0xC0DE (49374)
Author-email: winder1492@gmail.com
License: UNKNOWN
Download-URL: https://github.com/49374/OverTheShellbags.git
Platform: UNKNOWN
Classifier: Programming Language :: Python :: 3
Classifier: License :: OSI Approved :: MIT License
Requires-Python: >=3
